path_util/__init__.py
path_util/path.py
path_util/path_util.py
path_util-0.1.3.dist-info/WHEEL
path_util-0.1.3.dist-info/METADATA
path_util-0.1.3.dist-info/RECORD
